shellfmt/__init__.py
shellfmt/fmt_shell.py
shellfmt-0.1.2.dist-info/METADATA
shellfmt-0.1.2.dist-info/WHEEL
shellfmt-0.1.2.dist-info/entry_points.txt
shellfmt-0.1.2.dist-info/top_level.txt
shellfmt-0.1.2.dist-info/RECORD
