Metadata-Version: 2.1
Name: shellfmt
Version: 0.1.2
Summary: format .sh file
Home-page: https://github.com/xmxoxo/
Author: He xi
Author-email: xmhexi@qq.com
License: UNKNOWN
Project-URL: Blog, https://blog.csdn.net/xmxoxo
Keywords: shell file(.sh) formt tool
Platform: UNKNOWN
Classifier: Development Status :: 5 - Production/Stable
Classifier: Intended Audience :: Developers
Classifier: Topic :: Software Development :: Code Generators
Classifier: License :: OSI Approved :: MIT License
Classifier: Programming Language :: Python :: 3
Classifier: Programming Language :: Python :: 3.4
Classifier: Programming Language :: Python :: 3.5
Classifier: Programming Language :: Python :: 3.6
Classifier: Programming Language :: Python :: 3.7
Classifier: Programming Language :: Python :: 3.8
